bencheval/__init__.py
bencheval/data/__init__.py
bencheval/data/__pycache__/__init__.cpython-38.pyc
bencheval/data/bbh/__init__.py
bencheval/data/bbh/cols.txt
bencheval/data/bbh/format.py
bencheval/data/bbh/leaderboard.tsv
bencheval/data/bbh/statistic.py
bencheval/data/bbh/vanilla.tsv
bencheval/data/bigcode/__init__.py
bencheval/data/bigcode/format.py
bencheval/data/bigcode/leaderboard.tsv
bencheval/data/bigcode/vanilla.txt
bencheval/data/dummy/__init__.py
bencheval/data/glue/__init__.py
bencheval/data/glue/leaderboard.tsv
bencheval/data/heim/__init__.py
bencheval/data/heim/aesthetics_auto.tsv
bencheval/data/heim/aesthetics_human.tsv
bencheval/data/heim/alignment_auto.tsv
bencheval/data/heim/alignment_human.tsv
bencheval/data/heim/black_out.tsv
bencheval/data/heim/nsfw.tsv
bencheval/data/heim/nudity.tsv
bencheval/data/heim/originality.tsv
bencheval/data/heim/quality_auto.tsv
bencheval/data/heim/quality_human.tsv
bencheval/data/helm/__init__.py
bencheval/data/helm/accuracy.tsv
bencheval/data/helm/bias.tsv
bencheval/data/helm/calibration.tsv
bencheval/data/helm/efficiency.tsv
bencheval/data/helm/fairness.tsv
bencheval/data/helm/robustness.tsv
bencheval/data/helm/summarization.tsv
bencheval/data/helm/toxicity.tsv
bencheval/data/imagenet/__init__.py
bencheval/data/imagenet/format.py
bencheval/data/imagenet/leaderboard.tsv
bencheval/data/imagenet/leaderboard_raw.tsv
bencheval/data/imagenet/run.sh
bencheval/data/imagenet/run_imagenet.py
bencheval/data/imagenet/vanilla.txt
bencheval/data/mmlu/__init__.py
bencheval/data/mmlu/format.py
bencheval/data/mmlu/leaderboard.tsv
bencheval/data/mmlu/leaderboard_raw.csv
bencheval/data/mteb/__init__.py
bencheval/data/mteb/format.py
bencheval/data/mteb/leaderboard.tsv
bencheval/data/mteb/vanilla.txt
bencheval/data/openllm/__init__.py
bencheval/data/openllm/format.py
bencheval/data/openllm/leaderboard.tsv
bencheval/data/openllm/statistic.py
bencheval/data/openllm/vanilla.txt
bencheval/data/superglue/__init__.py
bencheval-1.11.dist-info/METADATA
bencheval-1.11.dist-info/WHEEL
bencheval-1.11.dist-info/top_level.txt
bencheval-1.11.dist-info/RECORD
